{"data":[{"Type":"Friends","SubType":"General","Caption":"When worst comes to worst, squad comes first."},{"Type":"Friends","SubType":"General","Caption":"You simply cannot do epic things with boring people."},{"Type":"Friends","SubType":"General","Caption":"Friends that travel together stay together."},{"Type":"Friends","SubType":"General","Caption":"Squad means family and family means nobody gets left behind."},{"Type":"Friends","SubType":"General","Caption":"Good Times + Crazy Friends = Great Memories!"},{"Type":"Friends","SubType":"General","Caption":"There is nothing better than a good friend, except for a good friend with chocolate."},{"Type":"Friends","SubType":"Party","Caption":"Beer is better when you drink together."},{"Type":"Friends","SubType":"Party","Caption":"The best beers are the ones we drink with friends."},{"Type":"Friends","SubType":"General","Caption":"Hard times will always reveal true friends."},{"Type":"Friends","SubType":"General","Caption":"Friends till the end!"},{"Type":"Friends","SubType":"General","Caption":"True friends never apart. Maybe in distance, but never in heart."},{"Type":"Friends","SubType":"General","Caption":"Real men don’t take selfies."},{"Type":"Friends","SubType":"General","Caption":"There are big ships and small ships. But the best ship is FRIENDSHIP!"},{"Type":"Friends","SubType":"General","Caption":"All the best people are crazy."},{"Type":"Friends","SubType":"General","Caption":"When worst comes to worst, squad comes first."},{"Type":"Friends","SubType":"General","Caption":"You simply cannot do epic things with boring people."},{"Type":"Friends","SubType":"General","Caption":"Friends that travel together stay together."},{"Type":"Friends","SubType":"General","Caption":"Squad means family and family means nobody gets left behind."},{"Type":"Friends","SubType":"General","Caption":"Good Times + Crazy Friends = Great Memories!"},{"Type":"Friends","SubType":"General","Caption":"There is nothing better than a good friend, except for a good friend with chocolate."},{"Type":"Friends","SubType":"Party","Caption":"Beer is better when you drink together."},{"Type":"Friends","SubType":"Party","Caption":"The best beers are the ones we drink with friends."},{"Type":"Friends","SubType":"General","Caption":"Hard times will always reveal true friends."},{"Type":"Friends","SubType":"General","Caption":"Friends till the end!"},{"Type":"Friends","SubType":"General","Caption":"True friends never apart. Maybe in distance, but never in heart."},{"Type":"Friends","SubType":"General","Caption":"Real men don’t take selfies."},{"Type":"Friends","SubType":"General","Caption":"There are big ships and small ships. But the best ship is FRIENDSHIP!"},{"Type":"Friends","SubType":"General","Caption":"All the best people are crazy."}]}